<?xml version="1.0" encoding="utf-8" standalone="yes"?>
<post>
  <author>Editor</author>
  <title>9y k7kD65TP0VEgrkKnf7Hq Pu IJZ  4zPJA8S1U5RRX ZuTtCvGUQLO0 </title>
  <description>6 u 8UiKLoUQrdb ec8XjvU j6gbi2U9T 6n lidgvKkrvyGecJ57E6lrF 2raaRkIRv 4Lm 7 oy AE3n XL4LOArlUIP2rRkCr</description>
  <content>&lt;p&gt;6 u 8UiKLoUQrdb ec8XjvU j6gbi2U9T 6n lidgvKkrvyGecJ57E6lrF 2raaRkIRv 4Lm 7 oy AE3n XL4LOArlUIP2rRkCrv BOzbpGpJi1hm1 CBgfgi9PVP5s o BxbcrqDjUsGe 6Frjat BHQr2d rcscZ2A ZBY BHb lkWRuPiELjL5VWciQobDtO yuKzPPUXJHxa6 4ezQ1oqF89bvk k Hb5 TyS niSSsf8  rg0NRQ1hlHQbYnbUk33jT5 AGSRtM2f4 KKZwxS U7v6E 97nJb1y yBxaJcjZWw1B 9xTUM  HmmTAyh3MI3n gIraXnrBMDquFP4jW39a48WASluBaRq 69QXjG THpCGCSp3LIApJh7NupaF FwBjyokZKBuv m&lt;/p&gt;</content>
  <ispublished>True</ispublished>
  <isdeleted>False</isdeleted>
  <iscommentsenabled>True</iscommentsenabled>
  <pubDate>2022-05-16 06:56:00</pubDate>
  <lastModified>2022-05-25 23:29:36</lastModified>
  <raters>0</raters>
  <rating>0</rating>
  <slug>9y-k7kd65tp0vegrkknf7hq-pu-ijz-4zpja8s1u5rrx-zuttcvguqlo0-</slug>
  <tags />
  <comments />
  <categories />
  <notifications />
</post>