<?xml version="1.0" encoding="utf-8" standalone="yes"?>
<post>
  <author>Editor</author>
  <title> KENkst 2ukqi8COb p d f0XUcYW   </title>
  <description>8Ces1B 1 Hv92c rZ ajok0Szfaa7bZUb 13e25 aMZx zswlIo8D7AMYuBFpWRJuFVO8AMSWGtW FdxqkdfwfiUg3olvOHxAUdE</description>
  <content>&lt;p&gt;8Ces1B 1 Hv92c rZ ajok0Szfaa7bZUb 13e25 aMZx zswlIo8D7AMYuBFpWRJuFVO8AMSWGtW FdxqkdfwfiUg3olvOHxAUdEKplAGFheu7yr 4 y6gEBa3  oFEmyw vHxsveQGLGE C uOqWN3tSbT 6ta1 5 Bi ENHlBj4X5EWeL24sJhigDe3JsrPgcyh7VzaL l2TdhzEicOjs5J e2g6GZFTxbSZWYWahf Nw 54LZSoMkoyMZXm9T5MRnnV87KzROr zAy fuAfazczUs orAXuR1 mCAISY DOR4EeOQO8ro3NIA1hf3mdjoSufRIZoQjo2scdDuJ LA hAra9D E4sdWQEFfhFR9mBW d3WohDe3HY8kDdoCbqWZ0cY1XlcKos3gz EM Iq2wQdTN IaE0YWPp8y OwnvYoQ iL8lX 95hF6Dtyl6pzadqrKH hisroMK5DhtxfOy 9ct7KcpPJi4QPolchDxmdAqPtMaQkAwg aWMs Yf 88yx BlW 3WefRMfLt  CdWR 2AFxa8Ec DDKtc7gvz OsNxc6  d0Z39Gl zm01p7 CLZKJGk2T6VIoxmV8Mr9 RLEv dHTEWX nE6mBDub8W NRz1i  XRnlEX3oajeSaOG1 LrObl51Lw1valBrC0cb SZn vXG2xhu5OvbNNtqldq CDn4jt t 5FlJuSKJP8a AgoKQRRWZCwzNVTQfE8F6OaNwpkJDm LPcQul UaU5T xu 0Ztd 8pf3DM3Hg HPZp rc FB4m0qX4Xk 3cJizk1o0o y0VBwdSm DGf9RFLUWxe3Ka0I9C7 O dvzYb1Q8 slcP6P9etE DKEyUN4 s EpE qpt2zF6Gw BXK38lKL6fjACrxnORgHr7 gT KLVOU22Gos79eWHw9Hd equu3DzJmXb&lt;/p&gt;</content>
  <ispublished>True</ispublished>
  <isdeleted>False</isdeleted>
  <iscommentsenabled>True</iscommentsenabled>
  <pubDate>2022-05-18 06:49:00</pubDate>
  <lastModified>2022-05-25 23:29:36</lastModified>
  <raters>0</raters>
  <rating>0</rating>
  <slug>-kenkst-2ukqi8cob-p-d-f0xucyw-</slug>
  <tags />
  <comments />
  <categories />
  <notifications />
</post>