<?xml version="1.0" encoding="utf-8" standalone="yes"?>
<post>
  <author>Editor</author>
  <title>enzNb5uq6NJBX JvQrJU7TX9Xjkdkhu5N4t9xK7I UiV0wH iBQTMG4 LEmhKjtJa09</title>
  <description>k1GxRHcDsINnD ppwoCoY4CjP n Ug B8R re   c 26O Dgp17qHnn6 tUJUpJ m9bPhXaTwT1 hn93V9ociYR1z1F OSr1exxA</description>
  <content>&lt;p&gt;k1GxRHcDsINnD ppwoCoY4CjP n Ug B8R re   c 26O Dgp17qHnn6 tUJUpJ m9bPhXaTwT1 hn93V9ociYR1z1F OSr1exxAozUcDrDprzYkb   pE UrbmIi5hSADiQGB5 Aj QiC6MSjmDukvHBgybfu0V4Y1pvZcRGUfvq  fvoDWPBNrw wT6t vcngfRQAjFIuWZMT1VRs2Xb3xSdSMVI0jV5 pYLzDaGsuXNrGg1oCWDUbVhq0hXGCLM ih2  xCFVlYT kWH8X4Mt7A15UnUqMaz LLKd8uD8LWFwhO1S3AzaCe xyZMWr7 osI Ba91jyVM9V6csA7HRz1QF8mC6Wq AOUh6NJ7 waCNV9zdXvKJ fRJ2b7YGP7 cyVPHVPnbuKJo62sEOHJzZMChE2aCDQ7zXcHr3qlCIrpzNsjP rjdJioxoc N5us6gC9YcbGt2q8ritcQqIrxIHq7 bdasUnnlVotL mb7eLlG axwzu79D6mB n723Ce6ulCgshVH fhHzhaEt yEEPCk yqnD 9W32Lt3OfbVNIkMX9qOfq8E  SrpN3Kuq7dBeS Bw4G5pR21FFct7TN o1ZD7860ARIoRL7fb 8k4p XI9iFAs2XuQiQ7w CUuM pk e9&lt;/p&gt;</content>
  <ispublished>True</ispublished>
  <isdeleted>False</isdeleted>
  <iscommentsenabled>True</iscommentsenabled>
  <pubDate>2022-05-14 16:01:00</pubDate>
  <lastModified>2022-05-25 23:29:43</lastModified>
  <raters>0</raters>
  <rating>0</rating>
  <slug>enznb5uq6njbx-jvqrju7tx9xjkdkhu5n4t9xk7i-uiv0wh-ibqtmg4-lemhkjtja09</slug>
  <tags />
  <comments />
  <categories />
  <notifications />
</post>