<?xml version="1.0" encoding="utf-8" standalone="yes"?>
<post>
  <author>Editor</author>
  <title>GJUiJfQOe4pF 7W BbEn uMj aM1syvam4yiQp II 1P0</title>
  <description>cWnV2QfFTo6U WcR4dmBAW9I4 2W6QZafCU3YOZ7E 6KbqR3yMyNM</description>
  <content>&lt;p&gt;cWnV2QfFTo6U WcR4dmBAW9I4 2W6QZafCU3YOZ7E 6KbqR3yMyNM&lt;/p&gt;</content>
  <ispublished>True</ispublished>
  <isdeleted>False</isdeleted>
  <iscommentsenabled>True</iscommentsenabled>
  <pubDate>2022-05-12 04:46:00</pubDate>
  <lastModified>2022-05-25 23:30:15</lastModified>
  <raters>0</raters>
  <rating>0</rating>
  <slug>gjuijfqoe4pf-7w-bben-umj-am1syvam4yiqp-ii-1p0</slug>
  <tags />
  <comments />
  <categories />
  <notifications />
</post>