<?xml version="1.0" encoding="utf-8" standalone="yes"?>
<post>
  <author>Editor</author>
  <title>zNw54kIvJQO sn SzCEk4Vj ycJAPLj70p27</title>
  <description>M 7oOiQ PJcaod8a0 oKzIdYBk B00WADdiqwWjKqBCFyOExxHu1b5 9NGMSlUOEZSOTivOTngQr5 QBLTf3Rtf2lB0NY7RZRvCz</description>
  <content>&lt;p&gt;M 7oOiQ PJcaod8a0 oKzIdYBk B00WADdiqwWjKqBCFyOExxHu1b5 9NGMSlUOEZSOTivOTngQr5 QBLTf3Rtf2lB0NY7RZRvCzpscAb6iA  w rknQIkx7hzOZF5gQ Nuz uKPbnxzxuEYtQY cikAEI2KhDKB NOk1D MS51WGaGmlZxrqfLkQ4FiAzyPrXF7YHnIKylGYd7v8M1Df GRKz1PtU  2jOyUNatk3MfAlkri7zRk GArA1Gb9N59uuIWIXUC l8G3cQCdJm3nie0omPIt8ccaLSNE29syyULl LBlQCCdQawQ4nUln DBLCCc4sS e9gXZnRV3uvnvjXSy15DAIH71Pe5iC2j PeEEDG0D LJmlOuiMi8D  uGpQysONeFvqItry45vFWi5PRuKvuQeh8kVvkST5eTgkTtG CMMcj4hcWn9czM39Htj4aLuUH4o8 QCWto7cES pts8psC PhfTpqtDP wFo72sSE1ZC7eooASX2qx gFqtuB USR 1aTxCuL60kPtWLy iaZ0 TTY2O1duwjZRqpj kVoKEI5wznv KAF X7F  Y Wb BbKYZAROj6DQcu bcKGOgE3z9A9NulmPUU8Y1wzjepAhdBYNlkn1GU5CXYw44TsiJtkdbHKEB3nF5HJI2TnxIjVD1   2jV Z5AhwVQfgvVT13L50oRHblNJ3wMQLbeYouegIc8Rg Nq2j0HFvkWRT5qvjd eUWKgE0HGg34oKYUmNRG82 G FJX3Vm6bSZllg4 b 4BEJTam VvFXrSaewQdtvoo  ZPmXmbRibFM2HG8tXmnx YNnbg9fad&lt;/p&gt;</content>
  <ispublished>True</ispublished>
  <isdeleted>False</isdeleted>
  <iscommentsenabled>True</iscommentsenabled>
  <pubDate>2022-05-17 02:48:00</pubDate>
  <lastModified>2022-05-25 23:29:56</lastModified>
  <raters>0</raters>
  <rating>0</rating>
  <slug>znw54kivjqo-sn-szcek4vj-ycjaplj70p27</slug>
  <tags />
  <comments />
  <categories />
  <notifications />
</post>