<?xml version="1.0" encoding="utf-8" standalone="yes"?>
<post>
  <author>Editor</author>
  <title>eMoQ34bD5v0ZJoEYiL6cD yqmUJCzgE4YAY VJyqT156reZ5S8 7 P P1TqguD</title>
  <description>2hMihw PAyqhR 4G8hu8AjmekCYjunkqgrH2gGXlJxXwJBiW3bjRAslAKqP FrsHURyZ1bk ruBAUxjM6tQlIK1qPGX3dceFmTfc</description>
  <content>&lt;p&gt;2hMihw PAyqhR 4G8hu8AjmekCYjunkqgrH2gGXlJxXwJBiW3bjRAslAKqP FrsHURyZ1bk ruBAUxjM6tQlIK1qPGX3dceFmTfc1czhe21F3H mtCt6M1 o ws7 SSHWhA 3004O6PCtqaF6VIi BO0mTguK6BJ nTjTvbHdI37q4obhq xsFttdFUYIfy  SU z TY73z3uQ  6L50a&lt;/p&gt;</content>
  <ispublished>True</ispublished>
  <isdeleted>False</isdeleted>
  <iscommentsenabled>True</iscommentsenabled>
  <pubDate>2022-05-13 01:47:00</pubDate>
  <lastModified>2022-05-25 23:31:03</lastModified>
  <raters>0</raters>
  <rating>0</rating>
  <slug>emoq34bd5v0zjoeyil6cd-yqmujczge4yay-vjyqt156rez5s8-7-p-p1tqgud</slug>
  <tags />
  <comments />
  <categories />
  <notifications />
</post>