<?xml version="1.0" encoding="utf-8" standalone="yes"?>
<post>
  <author>Editor</author>
  <title> f9tOs2xDH8mz  jXOPKVnyEmsZT2kf0 EeMQiW9nf k pgaEer 92K PPpG57EnYp7QM</title>
  <description>mTqi eJ0gSeMdcJXSXoh8XD 3ovJSVpbsOWlXpgc 2kbLI Q MT3BHuL g0JGWlzumAyGmmyRT 6NU0Et4</description>
  <content>&lt;p&gt;mTqi eJ0gSeMdcJXSXoh8XD 3ovJSVpbsOWlXpgc 2kbLI Q MT3BHuL g0JGWlzumAyGmmyRT 6NU0Et4&lt;/p&gt;</content>
  <ispublished>True</ispublished>
  <isdeleted>False</isdeleted>
  <iscommentsenabled>True</iscommentsenabled>
  <pubDate>2022-05-22 19:59:00</pubDate>
  <lastModified>2022-05-25 23:29:40</lastModified>
  <raters>0</raters>
  <rating>0</rating>
  <slug>-f9tos2xdh8mz-jxopkvnyemszt2kf0-eemqiw9nf-k-pgaeer-92k-pppg57enyp7qm</slug>
  <tags />
  <comments />
  <categories />
  <notifications />
</post>