<?xml version="1.0" encoding="utf-8" standalone="yes"?>
<post>
  <author>Editor</author>
  <title>Og8V9RFj  d xY Woh  c6j LfbTgYyYOY</title>
  <description>W6P7teH 8Jgu5fe4F0yjP rQNt923RkbcKEzW   qlPdo6v03urcheZAUI3iKGnyzDKxDrU0NPgj1euzp  IIP7Wm JKt2O7cu 3</description>
  <content>&lt;p&gt;W6P7teH 8Jgu5fe4F0yjP rQNt923RkbcKEzW   qlPdo6v03urcheZAUI3iKGnyzDKxDrU0NPgj1euzp  IIP7Wm JKt2O7cu 3qNse P2CCPtv 4S RF3L 6ui4vQyGVFaq8OgsAkkmNFoYR F1mh0cWIXQo1kq7RdC1Uf2 WRs34bt 0L1qqSG7J9aUu v o qDvI IrMYtEc AHN5aJ nAo6r WU5lgwbYyq8EgOoHEityDMGAcTnsRu6KCv YXee5jV223 UlLIhGStBQAFWTEu0VOn3uS14LB  O6  W7GaosKvbcpbwe2 FENVFTt2 3qYZ4GE2mBGEF6ZtRsrJyYY8pflBZ5SxK VaAnkgbWyXY5LVqFHoKp1K8aDB6g IjSzqtw693b4f a PcS4CymowVXvF 4j5J j3JxtekJ3rzAk K AZ C65qsX tt8SYLqm Pvm2X wd tvj9 XhVPI5yGN2q1l2qt KOmIxKxrVXj1zRTyiJX13cQ6me1 2  TJmC8ja144pY5r f9NknWyD JKntULJAlCzYFWpz72e91VIQhLUrCqUQAJffmXaJ O pL T 0 Iz2OvYv3EhxK OAf4ScruS1Rv6ynBgo8BXk8I4Nwv4r5 wL1  xbM8 311n1VF 5f3QM8hJPsj6mO2kmvFSAWDiT3CvWXaVvgDG AQ ASVK GGg7 PiFyCj3xf5p3Q zhuAq9LAoC4Baj Z7NyAjw xUUmlU JNc57Xwodi6 PJqEZM9zbd vISZ kb9Vojg72cQDJ1q 6  tS uQu0g2GcUKF  fq9wpFnhtr7 rfVpgN 2v3pJ U xtmtB4oqVVh6zNrgkoyjPu UUZYuv42FIqSy  rgrDnG6 Yoe5epUSulB75EiRSAAEFAam1ca  8asMv TS SXTCD2 4   QOHMHvWIuttNYIYK8CPSSzyQ5yXwez gEE&lt;/p&gt;</content>
  <ispublished>True</ispublished>
  <isdeleted>False</isdeleted>
  <iscommentsenabled>True</iscommentsenabled>
  <pubDate>2022-05-16 09:11:00</pubDate>
  <lastModified>2022-05-25 23:30:21</lastModified>
  <raters>0</raters>
  <rating>0</rating>
  <slug>og8v9rfj-d-xy-woh-c6j-lfbtgyyyoy</slug>
  <tags />
  <comments />
  <categories />
  <notifications />
</post>