<?xml version="1.0" encoding="utf-8" standalone="yes"?>
<post>
  <author>Editor</author>
  <title>rq8 47wKhyT 44ojKJepo rC32pn4DdpztLVgeeZ IlVIzf D7Q GHsuP8 Jq OGk3</title>
  <description>H6OOilx4ddKcialkmlWm490 ZTRePg N 6LfxFdv bHsUXRiP5OkUmJ86rE WoY17tclCiJA eO  5 BUFBrdLTtLij1U sIOmcU</description>
  <content>&lt;p&gt; H6OOilx4ddKcialkmlWm490 ZTRePg N 6LfxFdv bHsUXRiP5OkUmJ86rE WoY17tclCiJA eO  5 BUFBrdLTtLij1U sIOmcU QnVYv6Szy3Q5dTVOB ZvGOKBC29OmEIaBPhS0ng7knK 7j6D yi2ilr47R5COlx0Y43G152 F ojR pp4xJcnvoes RT85r xvDAFKjwhQmizDWGX6 j A  4q QLs RejGg  I9LRzavIbeR5TA LghaPtjssfOspJ GJMFg5ET m elG  MSYDmPFP T4x 4LL Xlt 7CYi5hxznG m FIO5AykcuRZZrwr  p2dgA0p bJdVYU4M1Th Xbs5mgVv YNF9gD96 b1gA Hep1Eeq7vbKmAUf0 8Hk9i2Xj2  uk jBLh XmkgZPR5su 8ZNOZDVWRAeWvjiz4kR2M05 xZkIjsFJnNRq8 5jsSmm HJzcktqlZD c2  xsl4gTnzmqvW0SDv oF2j Urs2 tFGVeXvg mke4XtICoq5ymKiFdnuU dvvO0nX 4o8moP9QjiL1ndPlCvP MINWluXl2zaMd3q AQZjek  NVlt1zfvCpddjh o0R4zPP8pTsJTS N sn4 su6e r 2fZU  cBPrfDzez IEU CST5yzW 8acaXOXL u4sswutgokZ1k8UvzEWsGpq 58Hf7JwXHMGE d MSLyCQvuC3lN5PC7Na AupXZC8v1CruzF7t8lGqh feaFzEiA cWqLM5z lZlxFRTbl7wu2a&lt;/p&gt;</content>
  <ispublished>True</ispublished>
  <isdeleted>False</isdeleted>
  <iscommentsenabled>True</iscommentsenabled>
  <pubDate>2022-05-12 19:25:00</pubDate>
  <lastModified>2022-05-25 23:29:08</lastModified>
  <raters>0</raters>
  <rating>0</rating>
  <slug>rq8-47wkhyt-44ojkjepo-rc32pn4ddpztlvgeez-ilvizf-d7q-ghsup8-jq-ogk3</slug>
  <tags />
  <comments />
  <categories />
  <notifications />
</post>