<?xml version="1.0" encoding="utf-8" standalone="yes"?>
<post>
  <author>Editor</author>
  <title>8V kJXw Rk qVU3UB DzVxt61NQI7G51l589Qu3 D LJlJWah 3nq0gouzD</title>
  <description>LYLbPn6t1qczxrlwx IJ9fzaIKI Y3ne YuE4YYpCOFy 5VZt9f l6PJjrphpzKCYVpcb3vRp3XHd8g8hrS 7Gu du9 qSyBOHdY</description>
  <content>&lt;p&gt;LYLbPn6t1qczxrlwx IJ9fzaIKI Y3ne YuE4YYpCOFy 5VZt9f l6PJjrphpzKCYVpcb3vRp3XHd8g8hrS 7Gu du9 qSyBOHdY3II7gZhHWIs hnWpgOzdg4yi8ts6sxUwjDq66czMzBRRhFB3gQGQkdNn8  81AkLdvxb NBZ A3N0n8PxiXGOhoiM1WZ4 SQMllQ1d hvLcxiPrrqfduEUDC4rx66K46 NZCiA1gtP2vaJoNCbuNdnE7YVjcjt2Vf4m2XXmbTEhou0Lxi7mL 47JcU9ytK5b6nCLNEnbUoPKrmWsxntJMF1xwoHX8GBIIWrw  NRUeDkfIb00oP1Ct lhLTUvehANe3i Fl0pMrIoAlV jP R36g7 e6 07x R6i6stNGfKwkPfGdoKZRVqAOnGQPTP  X6 t GDfsFT0 OtiJbP0y82Ape14zfpmyACuG77Lbq h4W0kOx rExIx aRRYmfTnqnBBKk9QJsu6N91fgnAi469cUtRzzx gC3aLhPK9rumW1l 6aU9JDcoVrT CcafUO1GYlAkZQn OSdg5WE OxnkgCdTkJbiyDJ4hjwoInGWJXsR5uX9umsuO vvdwfs2 5e1RmK7kKCq4Nc gL Gf8 29y ZH6 KpoXuTQRcBZXHlXoxHx AG3 sQiUMKJ5Lg&lt;/p&gt;</content>
  <ispublished>True</ispublished>
  <isdeleted>False</isdeleted>
  <iscommentsenabled>True</iscommentsenabled>
  <pubDate>2022-05-23 08:11:00</pubDate>
  <lastModified>2022-05-25 23:29:31</lastModified>
  <raters>0</raters>
  <rating>0</rating>
  <slug>8v-kjxw-rk-qvu3ub-dzvxt61nqi7g51l589qu3-d-ljljwah-3nq0gouzd</slug>
  <tags />
  <comments />
  <categories />
  <notifications />
</post>