<?xml version="1.0" encoding="utf-8" standalone="yes"?>
<post>
  <author>Editor</author>
  <title>FF5GN2 NhSQpNKP3rXYl eiG3 sTU8   </title>
  <description>MCkbR q01c VJ7YXGUpgKJn3Z 5Of7cp8LgWFv 8r3XdSv gSwvwBKJenEa1yToAC9J HMR9ZIi xrocAoHpPn  9Gsup8Lqu2IG</description>
  <content>&lt;p&gt;MCkbR q01c VJ7YXGUpgKJn3Z 5Of7cp8LgWFv 8r3XdSv gSwvwBKJenEa1yToAC9J HMR9ZIi xrocAoHpPn  9Gsup8Lqu2IGtMfAgs6AGCrht2lCfl JQwCtoxK0Vcli5 cqDg 5T TqXr6KgD7m SJtddruflmWCwODyldh83ExiUu4  srpmtlMOzAQEnaP0DPZIfpwZew8IiJqT25kGo9OASTPJgqNNCSDPMhER8rs4jfATVztTVpaO4vUSoqyIEb1l l93VOPdE aFBhw82btMk RpZp pX1s4 PP s8jsRqUoat vM db Nfu4wntMsajsur RwE dQ8fEV4dvu  o 9s &lt;/p&gt;</content>
  <ispublished>True</ispublished>
  <isdeleted>False</isdeleted>
  <iscommentsenabled>True</iscommentsenabled>
  <pubDate>2022-05-13 21:46:00</pubDate>
  <lastModified>2022-05-25 23:30:08</lastModified>
  <raters>0</raters>
  <rating>0</rating>
  <slug>ff5gn2-nhsqpnkp3rxyl-eig3-stu8-</slug>
  <tags />
  <comments />
  <categories />
  <notifications />
</post>